pydefault/__init__.py
py_default-1.0.1.dist-info/LICENSE
py_default-1.0.1.dist-info/METADATA
py_default-1.0.1.dist-info/WHEEL
py_default-1.0.1.dist-info/top_level.txt
py_default-1.0.1.dist-info/RECORD
