Metadata-Version: 2.1
Name: py-default
Version: 1.0.1
Summary: Uniform Default Values for Python
Author-email: Carl Furtado <carlzfurtado@gmail.com>
License: MIT License
Project-URL: Homepage, https://github.com/User0332/py-default
Classifier: License :: OSI Approved :: MIT License
Requires-Python: >=3.10
License-File: LICENSE
